pulumi_dbtcloud/__init__.py
pulumi_dbtcloud/_inputs.py
pulumi_dbtcloud/_utilities.py
pulumi_dbtcloud/account_features.py
pulumi_dbtcloud/athena_credential.py
pulumi_dbtcloud/big_query_credential.py
pulumi_dbtcloud/bigquery_semantic_layer_credential.py
pulumi_dbtcloud/databricks_credential.py
pulumi_dbtcloud/databricks_semantic_layer_credential.py
pulumi_dbtcloud/environment.py
pulumi_dbtcloud/environment_variable.py
pulumi_dbtcloud/environment_variable_job_override.py
pulumi_dbtcloud/extended_attributes.py
pulumi_dbtcloud/fabric_credential.py
pulumi_dbtcloud/get_athena_credential.py
pulumi_dbtcloud/get_azure_dev_ops_project.py
pulumi_dbtcloud/get_azure_dev_ops_repository.py
pulumi_dbtcloud/get_big_query_credential.py
pulumi_dbtcloud/get_databricks_credential.py
pulumi_dbtcloud/get_environment.py
pulumi_dbtcloud/get_environment_variable.py
pulumi_dbtcloud/get_environments.py
pulumi_dbtcloud/get_extended_attributes.py
pulumi_dbtcloud/get_global_connection.py
pulumi_dbtcloud/get_global_connections.py
pulumi_dbtcloud/get_group.py
pulumi_dbtcloud/get_group_users.py
pulumi_dbtcloud/get_groups.py
pulumi_dbtcloud/get_job.py
pulumi_dbtcloud/get_jobs.py
pulumi_dbtcloud/get_model_notifications.py
pulumi_dbtcloud/get_notification.py
pulumi_dbtcloud/get_postgres_credential.py
pulumi_dbtcloud/get_privatelink_endpoint.py
pulumi_dbtcloud/get_privatelink_endpoints.py
pulumi_dbtcloud/get_project.py
pulumi_dbtcloud/get_projects.py
pulumi_dbtcloud/get_redshift_credential.py
pulumi_dbtcloud/get_repository.py
pulumi_dbtcloud/get_runs.py
pulumi_dbtcloud/get_service_token.py
pulumi_dbtcloud/get_snowflake_credential.py
pulumi_dbtcloud/get_spark_credential.py
pulumi_dbtcloud/get_starburst_credential.py
pulumi_dbtcloud/get_synapse_credential.py
pulumi_dbtcloud/get_teradata_credential.py
pulumi_dbtcloud/get_user.py
pulumi_dbtcloud/get_user_groups.py
pulumi_dbtcloud/get_users.py
pulumi_dbtcloud/get_webhook.py
pulumi_dbtcloud/global_connection.py
pulumi_dbtcloud/group.py
pulumi_dbtcloud-1.4.1.dist-info/METADATA
pulumi_dbtcloud-1.4.1.dist-info/WHEEL
pulumi_dbtcloud-1.4.1.dist-info/top_level.txt
pulumi_dbtcloud-1.4.1.dist-info/RECORD
